MCPCurrentTime/MCPCurrentTime.py
MCPCurrentTime/__init__.py
MCPCurrentTime/requirements.txt
mcpcurrenttime-0.0.3.dist-info/METADATA
mcpcurrenttime-0.0.3.dist-info/WHEEL
mcpcurrenttime-0.0.3.dist-info/licenses/LICENSE
mcpcurrenttime-0.0.3.dist-info/RECORD
