Metadata-Version: 2.4
Name: MCPCurrentTime
Version: 0.0.3
Summary: A simple MCP server providing a single tool that agents can use to get the current time in a given timezone.
Project-URL: Homepage, https://github.com/mattjwarren/MCPCurrentTime
Project-URL: Issues, https://github.com/mattjwarren/MCPCurrentTime/issues
Author-email: Matthew Warren <matt.j.warren@gmail.com>
License-Expression: MIT
License-File: LICENSE
Classifier: Operating System :: OS Independent
Classifier: Programming Language :: Python :: 3
Requires-Python: >=3.9
Requires-Dist: mcp
Requires-Dist: pytz
